pymince/__init__.py
pymince/_constants.py
pymince/algorithm.py
pymince/benchmark.py
pymince/boolean.py
pymince/dates.py
pymince/dictionary.py
pymince/file.py
pymince/functional.py
pymince/iterator.py
pymince/json.py
pymince/logging.py
pymince/patterns.py
pymince/std.py
pymince/text.py
pymince/warnings.py
pymince/xml.py
pymince-2.13.0.dist-info/LICENSE
pymince-2.13.0.dist-info/METADATA
pymince-2.13.0.dist-info/WHEEL
pymince-2.13.0.dist-info/top_level.txt
pymince-2.13.0.dist-info/RECORD
