Metadata-Version: 2.1
Name: pymince
Version: 2.13.0
Summary: Python shredded utilities
Home-page: https://github.com/rmoralespp/pymince
Author: rmoralespp
Author-email: rmoralespp@gmail.com
License: MIT
Classifier: Programming Language :: Python
Classifier: Programming Language :: Python :: 3 :: Only
Classifier: Programming Language :: Python :: 3.8
Classifier: Programming Language :: Python :: 3.9
Classifier: Programming Language :: Python :: 3.10
Classifier: Programming Language :: Python :: 3.11
Classifier: Programming Language :: Python :: 3.12
Classifier: Programming Language :: Python :: 3.13
Classifier: Intended Audience :: Developers
Classifier: Intended Audience :: Information Technology
Classifier: Topic :: Software Development :: Libraries :: Python Modules
Classifier: Topic :: Internet
Classifier: Topic :: Utilities
Requires-Python: >=3.8
License-File: LICENSE
